optimum/furiosa/__init__.py
optimum/furiosa/configuration.py
optimum/furiosa/modeling.py
optimum/furiosa/modeling_base.py
optimum/furiosa/quantization.py
optimum/furiosa/quantization_base.py
optimum/furiosa/utils.py
optimum/furiosa/version.py
optimum_furiosa-0.1.0.dist-info/LICENSE
optimum_furiosa-0.1.0.dist-info/METADATA
optimum_furiosa-0.1.0.dist-info/WHEEL
optimum_furiosa-0.1.0.dist-info/entry_points.txt
optimum_furiosa-0.1.0.dist-info/top_level.txt
optimum_furiosa-0.1.0.dist-info/RECORD
