Metadata-Version: 2.1
Name: optimum-furiosa
Version: 0.1.0
Summary: Optimum Furiosa is the interface between the 🤗 Transformers library and Furiosa NPUs such as Furiosa Warboy. It provides a set of tools enabling easy model loading and inference for different downstream tasks for Furiosa NPU.
Home-page: https://huggingface.co/hardware
Author: HuggingFace Inc. Special Ops Team
Author-email: hardware@huggingface.co
License: Apache
Keywords: transformers,quantization,pruning,knowledge distillation,optimization,training
Classifier: Development Status :: 5 - Production/Stable
Classifier: License :: OSI Approved :: Apache Software License
Classifier: Intended Audience :: Developers
Classifier: Intended Audience :: Education
Classifier: Intended Audience :: Science/Research
Classifier: Operating System :: OS Independent
Classifier: Programming Language :: Python :: 3.7
Classifier: Programming Language :: Python :: 3.8
Classifier: Programming Language :: Python :: 3.9
Classifier: Topic :: Scientific/Engineering :: Artificial Intelligence
License-File: LICENSE
Requires-Dist: optimum (>=1.8.0)
Requires-Dist: transformers (>=4.20.0)
Requires-Dist: datasets (>=1.4.0)
Requires-Dist: furiosa-optimizer
Requires-Dist: furiosa-quantizer (==0.9.0)
Requires-Dist: furiosa-quantizer-impl (==0.9.1)
Requires-Dist: furiosa-sdk
Requires-Dist: onnx (>=1.12.0)
Requires-Dist: sentencepiece
Requires-Dist: scipy
Provides-Extra: quality
Requires-Dist: black (~=23.1) ; extra == 'quality'
Requires-Dist: ruff (>=0.0.241) ; extra == 'quality'
Provides-Extra: testing
Requires-Dist: filelock ; extra == 'testing'
Requires-Dist: GitPython ; extra == 'testing'
Requires-Dist: parameterized ; extra == 'testing'
Requires-Dist: psutil ; extra == 'testing'
Requires-Dist: pytest ; extra == 'testing'
Requires-Dist: pytest-pythonpath ; extra == 'testing'
Requires-Dist: pytest-xdist ; extra == 'testing'
Requires-Dist: Pillow ; extra == 'testing'
Requires-Dist: librosa ; extra == 'testing'
Requires-Dist: soundfile ; extra == 'testing'
